LICENSE
MANIFEST.in
README.md
setup.cfg
setup.py
doxieautomator/__init__.py
doxieautomator/base.py
doxieautomator/doxie.py
doxieautomator/settings.py
doxieautomator.egg-info/PKG-INFO
doxieautomator.egg-info/SOURCES.txt
doxieautomator.egg-info/dependency_links.txt
doxieautomator.egg-info/requires.txt
doxieautomator.egg-info/top_level.txt