Metadata-Version: 1.1
Name: doxieautomator
Version: 0.21
Summary: Retrieves scans on your Doxie Go or Doxie Q, places them in a local directory.
Home-page: https://github.com/ninapavlich/doxie-automator
Author: Nina Pavlich
Author-email: nina@ninalp.com
License: MIT
Keywords: libraries,scanning
Platform: UNKNOWN
Classifier: Development Status :: 4 - Beta
Classifier: Intended Audience :: Developers
Classifier: License :: OSI Approved :: MIT License
Classifier: Natural Language :: English
Classifier: Operating System :: OS Independent
Classifier: Programming Language :: Python
